thaobool/__init__.py
thaobool/bool_alias.py
thaobool-0.1.dist-info/METADATA
thaobool-0.1.dist-info/WHEEL
thaobool-0.1.dist-info/top_level.txt
thaobool-0.1.dist-info/RECORD
