Metadata-Version: 2.1
Name: thaobool
Version: 0.1
Summary: A package to use 'Thao' as a synonym for True
Author: Thanh
Author-email: your_email@example.com
License: MIT
Classifier: Programming Language :: Python :: 3
Classifier: License :: OSI Approved :: MIT License
Classifier: Operating System :: OS Independent
Requires-Python: >=3.6
